drugs/__init__.py
drugs/cache.py
drugs/chemistry.py
drugs/constants.py
drugs/core.py
drugs/data_sources.py
drugs/id_mapping.py
drugs/pubchem_text.py
drugs/utils.py
drugs/features/__init__.py
drugs/features/embeddings/__init__.py
drugs/features/embeddings/esm.py
drugs/features/embeddings/path.py
drugs/features/embeddings/text.py
drugs-0.1.2.dist-info/METADATA
drugs-0.1.2.dist-info/WHEEL
drugs-0.1.2.dist-info/licenses/LICENSE
drugs-0.1.2.dist-info/RECORD
