Metadata-Version: 2.4
Name: drugs
Version: 0.1.2
Summary: A short description
Project-URL: Homepage, https://github.com/kharoh/drugs
Project-URL: Documentation, https://drugs.readthedocs.io
Project-URL: Repository, https://github.com/kharoh/drugs
Project-URL: Issues, https://github.com/kharoh/drugs/issues
Author-email: Kharoh <gaulu03@gmail.com>
License-Expression: MIT
License-File: LICENSE
Keywords: keyword1,keyword2
Classifier: Development Status :: 3 - Alpha
Classifier: Intended Audience :: Developers
Classifier: Programming Language :: Python :: 3
Classifier: Programming Language :: Python :: 3.9
Classifier: Programming Language :: Python :: 3.10
Classifier: Programming Language :: Python :: 3.11
Requires-Python: >=3.9
Requires-Dist: numpy>=1.20
Requires-Dist: requests>=2.31
Requires-Dist: selfies>=2.1.1
Provides-Extra: chem
Requires-Dist: rdkit-pypi>=2023.9.3; extra == 'chem'
Provides-Extra: dev
Requires-Dist: black>=23.0; extra == 'dev'
Requires-Dist: mypy>=1.0; extra == 'dev'
Requires-Dist: pytest-cov>=4.0; extra == 'dev'
Requires-Dist: pytest>=7.0; extra == 'dev'
Requires-Dist: ruff>=0.1; extra == 'dev'
Provides-Extra: docs
Requires-Dist: sphinx-rtd-theme>=1.0; extra == 'docs'
Requires-Dist: sphinx>=5.0; extra == 'docs'
